tgup/__init__.py
tgup/client.py
tgup/config.py
tgup/progress_bar.py
tgup/telegram_upload_client.py
tgup/upload.py
tgup/utils.py
tgup/video.py
tgup-0.1.7.dist-info/licenses/LICENSE
tgup-0.1.7.dist-info/METADATA
tgup-0.1.7.dist-info/WHEEL
tgup-0.1.7.dist-info/entry_points.txt
tgup-0.1.7.dist-info/top_level.txt
tgup-0.1.7.dist-info/RECORD
