Metadata-Version: 2.4
Name: tgup
Version: 0.1.7
Summary: Upload files to Telegram using your account
Author-email: John Toniutti <john.toniutti@gmail.com>
License-Expression: GPL-3.0-or-later
Project-URL: repository, https://github.com/jotonedev/tgup
Keywords: telegram-upload,telethon,telegram,upload
Classifier: Topic :: Multimedia
Classifier: Development Status :: 3 - Alpha
Classifier: Programming Language :: Python :: 3
Classifier: Programming Language :: Python :: 3.11
Classifier: Programming Language :: Python :: 3.12
Classifier: Programming Language :: Python :: 3.13
Requires-Python: >=3.11
License-File: LICENSE
Requires-Dist: cryptg>=0.5.0.post0
Requires-Dist: hachoir>=3.3.0
Requires-Dist: python-ffmpeg>=2.0.12
Requires-Dist: telethon>=1.39.0
Requires-Dist: tqdm>=4.67.1
Dynamic: license-file
